fivana/__init__.py
fivana/cloudtrailsdk/__init__.py
fivana/cloudtrailsdk/execptions.py
fivana/cloudtrailsdk/client/__init__.py
fivana/cloudtrailsdk/client/tracker.py
fivana/cloudtrailsdk/decorators/__init__.py
fivana/cloudtrailsdk/decorators/api_gateway_tracker.py
fivana/cloudtrailsdk/decorators/custom_tracker.py
fivana/cloudtrailsdk/decorators/exception_tracker.py
fivana/cloudtrailsdk/middleware/__init__.py
fivana/cloudtrailsdk/model/__init__.py
fivana/cloudtrailsdk/model/event.py
fivana/cloudtrailsdk/utils/__init__.py
fivana/cloudtrailsdk/utils/functions.py
tests/__init__.py
tests/conftest.py
tests/test_tracker.py
Fivana_CloudTrails_SDK-3.2.0.dist-info/LICENSE.txt
Fivana_CloudTrails_SDK-3.2.0.dist-info/METADATA
Fivana_CloudTrails_SDK-3.2.0.dist-info/WHEEL
Fivana_CloudTrails_SDK-3.2.0.dist-info/top_level.txt
Fivana_CloudTrails_SDK-3.2.0.dist-info/RECORD
