Metadata-Version: 2.1
Name: Fivana-CloudTrails-SDK
Version: 3.2.0
Summary: SDK for CloudTrails DevOps management FIVANA
Home-page: https://bitbucket.org/factorclick/fc-cloudtrails-sdk-py
Author: Reynier Lester Claro Escalona, Ernesto Herrera
Author-email: rclaro@fivana.com, eherrera@fivana.com
License: UNKNOWN
Platform: UNKNOWN
Classifier: Programming Language :: Python :: 3
Classifier: Operating System :: OS Independent
License-File: LICENSE.txt
